rigidbodyfit/__init__.py
rigidbodyfit/__main__.py
rigidbodyfit/arguments.py
rigidbodyfit/fit.py
rigidbodyfit/logger.py
rigidbodyfit/runner.py
rigidbodyfit/structure.py
rigidbodyfit/transformations.py
rigidbodyfit-1.2.1.dist-info/COPYING
rigidbodyfit-1.2.1.dist-info/LICENSE
rigidbodyfit-1.2.1.dist-info/METADATA
rigidbodyfit-1.2.1.dist-info/WHEEL
rigidbodyfit-1.2.1.dist-info/entry_points.txt
rigidbodyfit-1.2.1.dist-info/top_level.txt
rigidbodyfit-1.2.1.dist-info/RECORD
