Metadata-Version: 2.1
Name: rigidbodyfit
Version: 1.2.1
Summary: Align biomolecular structures with densities
Home-page: https://gitlab.com/cblau/rigidbodyfit
Author: Christian Blau
Author-email: cblau.mail@gmail.com
Project-URL: Bug Tracker, https://gitlab.com/cblau/rigidbodyfit/issues
Keywords: molecular dynamics,GROMACS
Classifier: Programming Language :: Python :: 3
Classifier: Programming Language :: Python :: 3 :: Only
Classifier: Development Status :: 4 - Beta
Classifier: License :: OSI Approved :: GNU General Public License v3 or later (GPLv3+)
Classifier: Operating System :: OS Independent
Requires-Python: >=3.8
License-File: LICENSE
License-File: COPYING
Requires-Dist: argparse
Requires-Dist: biopandas
Requires-Dist: mrcfile
Requires-Dist: rich
Requires-Dist: scipy (>=1.4)
